CHANGELOG.md
LICENSE
MANIFEST.in
setup.py
robocad/__init__.py
robocad/algaritm.py
robocad/shufflecad.py
robocad/studica.py
robocad/internal/__init__.py
robocad/internal/algaritm_internal.py
robocad/internal/studica_internal.py
robocad/internal/common/__init__.py
robocad/internal/common/connection.py
robocad/internal/common/connection_base.py
robocad/internal/common/connection_real.py
robocad/internal/common/connection_sim.py
robocad/internal/common/lidar.py
robocad/internal/common/robot.py
robocad/internal/common/robot_configuration.py
robocad/internal/common/shared.py
robocad/internal/common/updaters.py
robocad_py.egg-info/PKG-INFO
robocad_py.egg-info/SOURCES.txt
robocad_py.egg-info/dependency_links.txt
robocad_py.egg-info/requires.txt
robocad_py.egg-info/top_level.txt