Metadata-Version: 2.4
Name: robocad-py
Version: 1.3.5.0
Summary: python lib for real and virtual robots
Home-page: https://github.com/Soft-V/robocad-py
Author: Airat Abdrakov
Author-email: softvery@yandex.ru
License: MIT
Keywords: simulator,robotics,robot,3d,raspberry,control,robocad
Classifier: Development Status :: 5 - Production/Stable
Classifier: Intended Audience :: Education
Classifier: Operating System :: Microsoft :: Windows :: Windows 10
Classifier: Operating System :: Android
Classifier: Operating System :: POSIX :: Linux
Classifier: Operating System :: iOS
Classifier: License :: OSI Approved :: MIT License
Classifier: Programming Language :: Python :: 3
License-File: LICENSE
Requires-Dist: numpy
Requires-Dist: funcad
Requires-Dist: pyserial
Dynamic: author
Dynamic: author-email
Dynamic: classifier
Dynamic: description
Dynamic: home-page
Dynamic: keywords
Dynamic: license
Dynamic: license-file
Dynamic: requires-dist
Dynamic: summary
